{
  "publicPath": "/_nuxt/",
  "all": [
    "../server/index.spa.html",
    "../server/index.ssr.html",
    "173c8518f9810d63acf7.js",
    "1b877d8caa268cf1e76c.js",
    "1d98e81d47ceaf438fee.css",
    "246b415b69c4f9dcfda1.js",
    "3b0e3207b31ff69e1c58.css",
    "460721a3edf09a936742.js",
    "4e00b2bf83a22b3439a8.js",
    "5334953b68769e59ce37.css",
    "854140c5106254de9cbd.js",
    "892785931ff60af9a7c5.js",
    "94547d44581c105a59a3.css",
    "9863655425b21475c934.js",
    "LICENSES",
    "b6a66e511381062c8f05.js",
    "c878daac161a8e7b12ea.js",
    "e113be7d707e0eed6d00.css",
    "f0c0cd92fd322fb9778b.css",
    "f150bdb1bf9ca2193980.js",
    "f36a208bc59d00589b6f.js",
    "fc2e6f15a5142ddc50bf.js",
    "fonts/33bad29.eot",
    "fonts/535877f.woff",
    "fonts/5bec095.ttf",
    "fonts/732389d.ttf",
    "fonts/f69ab29.woff",
    "img/ba63bbc.svg",
    "img/ce7a891.png"
  ],
  "initial": [
    "4e00b2bf83a22b3439a8.js",
    "854140c5106254de9cbd.js",
    "1d98e81d47ceaf438fee.css",
    "b6a66e511381062c8f05.js",
    "5334953b68769e59ce37.css",
    "246b415b69c4f9dcfda1.js"
  ],
  "async": [
    "173c8518f9810d63acf7.js",
    "1b877d8caa268cf1e76c.js",
    "3b0e3207b31ff69e1c58.css",
    "460721a3edf09a936742.js",
    "892785931ff60af9a7c5.js",
    "94547d44581c105a59a3.css",
    "9863655425b21475c934.js",
    "c878daac161a8e7b12ea.js",
    "e113be7d707e0eed6d00.css",
    "f0c0cd92fd322fb9778b.css",
    "f150bdb1bf9ca2193980.js",
    "f36a208bc59d00589b6f.js",
    "fc2e6f15a5142ddc50bf.js"
  ],
  "modules": {
    "15977234": [
      10
    ],
    "22388632": [
      9,
      5,
      28,
      22,
      26,
      24,
      27
    ],
    "25416490": [
      9,
      5,
      28,
      22,
      26,
      24,
      27
    ],
    "32179842": [
      9,
      5,
      28,
      22,
      26,
      24,
      27
    ],
    "32498052": [
      10
    ],
    "33796562": [
      10
    ],
    "36652332": [
      4,
      15,
      23,
      25
    ],
    "38993301": [
      9,
      5,
      28,
      22,
      26,
      24,
      27
    ],
    "42849276": [
      10
    ],
    "46051207": [
      9,
      5,
      28,
      22,
      26,
      24,
      27
    ],
    "56735126": [
      10
    ],
    "75438818": [
      10
    ],
    "77839966": [
      6,
      20
    ],
    "65f120bd": [
      10
    ],
    "5eb3d24a": [
      9,
      5,
      28,
      22,
      26,
      24,
      27
    ],
    "68c42f79": [
      10
    ],
    "742375e4": [
      10
    ],
    "5a5fd0f0": [
      10
    ],
    "699a2424": [
      10
    ],
    "1132876a": [
      4,
      15,
      23,
      25
    ],
    "19a76bc8": [
      10
    ],
    "56447c52": [
      10
    ],
    "73fd48ff": [
      10
    ],
    "253b9562": [
      4,
      15,
      23,
      25
    ],
    "0220c16a": [
      10
    ],
    "5ec8cd49": [
      10
    ],
    "e0c2663e": [
      10
    ],
    "16f0c3a4": [
      10
    ],
    "12e01ec6": [
      10
    ],
    "87f16316": [
      4,
      15,
      23,
      25
    ],
    "07e97b38": [
      10
    ],
    "41b6ca68": [
      10
    ],
    "7d6e01b5": [
      4,
      15,
      23,
      25
    ],
    "39d7ba89": [
      9,
      5,
      28,
      22,
      26,
      24,
      27
    ],
    "3b5d93ea": [
      9,
      5,
      28,
      22,
      26,
      24,
      27
    ],
    "747e1343": [
      9,
      5,
      28,
      22,
      26,
      24,
      27
    ],
    "708a0d9a": [
      9,
      5,
      28,
      22,
      26,
      24,
      27
    ],
    "3c83d2f2": [
      9,
      5,
      28,
      22,
      26,
      24,
      27
    ],
    "0640f7fa": [
      9,
      5,
      28,
      22,
      26,
      24,
      27
    ],
    "cd0687cc": [
      9,
      5,
      28,
      22,
      26,
      24,
      27
    ],
    "14df8465": [
      9,
      5,
      28,
      22,
      26,
      24,
      27
    ],
    "f56e3fc6": [
      9,
      5,
      28,
      22,
      26,
      24,
      27
    ],
    "80e6a63a": [
      9,
      5,
      28,
      22,
      26,
      24,
      27
    ],
    "13447ed2": [
      9,
      5,
      28,
      22,
      26,
      24,
      27
    ],
    "7b1e496f": [
      9,
      5,
      28,
      22,
      26,
      24,
      27
    ],
    "b2522764": [
      9,
      5,
      28,
      22,
      26,
      24,
      27
    ],
    "3b3875a7": [
      9,
      5,
      28,
      22,
      26,
      24,
      27
    ],
    "1cc41abf": [
      9,
      5,
      28,
      22,
      26,
      24,
      27
    ],
    "75a26bc8": [
      9,
      5,
      28,
      22,
      26,
      24,
      27
    ],
    "0b6823d4": [
      9,
      5,
      28,
      22,
      26,
      24,
      27
    ],
    "7dca0c2c": [
      9,
      5,
      28,
      22,
      26,
      24,
      27
    ],
    "214f3ebe": [
      9,
      5,
      28,
      22,
      26,
      24,
      27
    ],
    "61f5594c": [
      9,
      5,
      28,
      22,
      26,
      24,
      27
    ],
    "07c3f70c": [
      9,
      5,
      28,
      22,
      26,
      24,
      27
    ],
    "33fd6561": [
      9,
      5,
      28,
      22,
      26,
      24,
      27
    ],
    "1f618559": [
      9,
      5,
      28,
      22,
      26,
      24,
      27
    ],
    "7817761b": [
      9,
      5,
      28,
      22,
      26,
      24,
      27
    ],
    "ba0af2d6": [
      9,
      5,
      28,
      22,
      26,
      24,
      27
    ],
    "97c7d002": [
      9,
      5,
      28,
      22,
      26,
      24,
      27
    ],
    "57808f75": [
      9,
      5,
      28,
      22,
      26,
      24,
      27
    ],
    "0f2ff784": [
      9,
      5,
      28,
      22,
      26,
      24,
      27
    ],
    "31fd773e": [
      9,
      5,
      28,
      22,
      26,
      24,
      27
    ],
    "c7dd0bb4": [
      9,
      5,
      28,
      22,
      26,
      24,
      27
    ],
    "af9106da": [
      9,
      5,
      28,
      22,
      26,
      24,
      27
    ],
    "540fd53d": [
      9,
      5,
      28,
      22,
      26,
      24,
      27
    ],
    "d5e407ae": [
      9,
      5,
      28,
      22,
      26,
      24,
      27
    ],
    "783ce131": [
      9,
      5,
      28,
      22,
      26,
      24,
      27
    ],
    "7b99739e": [
      9,
      5,
      28,
      22,
      26,
      24,
      27
    ],
    "2a07654e": [
      9,
      5,
      28,
      22,
      26,
      24,
      27
    ],
    "401c26ed": [
      9,
      5,
      28,
      22,
      26,
      24,
      27
    ],
    "66f918ac": [
      9,
      5,
      28,
      22,
      26,
      24,
      27
    ],
    "0b5451ac": [
      9,
      5,
      28,
      22,
      26,
      24,
      27
    ],
    "2b0566d4": [
      9,
      5,
      28,
      22,
      26,
      24,
      27
    ],
    "a55a1110": [
      9,
      5,
      28,
      22,
      26,
      24,
      27
    ],
    "021c29bd": [
      9,
      5,
      28,
      22,
      26,
      24,
      27
    ],
    "5965645e": [
      9,
      5,
      28,
      22,
      26,
      24,
      27
    ],
    "21643b06": [
      9,
      5,
      28,
      22,
      26,
      24,
      27
    ],
    "ea01c14e": [
      9,
      5,
      28,
      22,
      26,
      24,
      27
    ],
    "36ab6d9c": [
      9,
      5,
      28,
      22,
      26,
      24,
      27
    ],
    "228a2e2a": [
      9,
      5,
      28,
      22,
      26,
      24,
      27
    ],
    "28eaed25": [
      9,
      5,
      28,
      22,
      26,
      24,
      27
    ],
    "44f17bf6": [
      9,
      5,
      28,
      22,
      26,
      24,
      27
    ],
    "28142e32": [
      9,
      5,
      28,
      22,
      26,
      24,
      27
    ],
    "605756d4": [
      9,
      5,
      28,
      22,
      26,
      24,
      27
    ],
    "25773f52": [
      9,
      5,
      28,
      22,
      26,
      24,
      27
    ],
    "390149e9": [
      9,
      5,
      28,
      22,
      26,
      24,
      27
    ],
    "1b967438": [
      9,
      5,
      28,
      22,
      26,
      24,
      27
    ],
    "0d91f50c": [
      9,
      5,
      28,
      22,
      26,
      24,
      27
    ],
    "2df2a5c6": [
      10
    ],
    "15a7e1e8": [
      10
    ],
    "1aae4aee": [
      10
    ],
    "1a232e49": [
      10
    ],
    "0c0f9076": [
      4,
      15,
      23,
      25
    ],
    "a10cbe7a": [
      10
    ],
    "59fdd989": [
      10
    ],
    "1ee550b5": [
      10
    ],
    "2f158f84": [
      4,
      15,
      23,
      25
    ],
    "c7017a44": [
      10
    ],
    "18ab2268": [
      10
    ],
    "449f90e2": [
      10
    ],
    "78248c55": [
      4,
      15,
      23,
      25
    ],
    "7dbc8dba": [
      10
    ],
    "3374f361": [
      10
    ],
    "5234fea9": [
      10
    ],
    "391de02a": [
      10
    ],
    "09a4ad8a": [
      10
    ],
    "7cedb2e8": [
      10
    ],
    "7545c214": [
      10
    ],
    "32d0bec3": [
      10
    ],
    "502fd1f5": [
      4,
      15,
      23,
      25
    ],
    "e669136a": [
      4,
      15,
      23,
      25
    ],
    "c089c866": [
      10
    ],
    "59084ec2": [
      10
    ],
    "cf821c70": [
      10
    ],
    "208b498c": [
      10
    ],
    "7096c413": [
      10
    ],
    "5283a2dc": [
      10
    ],
    "0c62117e": [
      10
    ],
    "dea3c61c": [
      10
    ],
    "0c27e20d": [
      10
    ],
    "a4789b00": [
      10
    ],
    "85f3a966": [
      10
    ],
    "6f6c003c": [
      4,
      15,
      23,
      25
    ],
    "8cf6db1c": [
      4,
      15,
      23,
      25
    ],
    "6f852637": [
      4,
      15,
      23,
      25
    ],
    "199246f5": [
      4,
      15,
      23,
      25
    ],
    "ba21e9da": [
      10
    ],
    "15aad669": [
      10
    ],
    "7d5e7f76": [
      10
    ],
    "32e0012f": [
      10
    ],
    "5d6b9f86": [
      10
    ],
    "145dc472": [
      10
    ],
    "23c4cafe": [
      10
    ],
    "0f41fdfa": [
      10
    ],
    "706da90a": [
      10
    ],
    "e2ff0566": [
      10
    ],
    "706b632f": [
      10
    ],
    "0c862cb1": [
      10
    ],
    "abfeb698": [
      10
    ],
    "87d1aea4": [
      10
    ],
    "2c7eef7c": [
      10
    ],
    "8640bf42": [
      10
    ],
    "2aea7f5c": [
      4,
      15,
      23,
      25
    ],
    "cc515cf8": [
      4,
      15,
      23,
      25
    ],
    "7b88e6ff": [
      4,
      15,
      23,
      25
    ],
    "de237c76": [
      4,
      15,
      23,
      25
    ],
    "f081ec7a": [
      10
    ],
    "00b54d4e": [
      10
    ],
    "5bf6ed40": [
      10
    ],
    "3b4eb327": [
      10
    ],
    "2f440cf2": [
      10
    ],
    "34f84b8e": [
      10
    ],
    "4f8aec77": [
      9,
      5,
      28,
      22,
      26,
      24,
      27
    ],
    "097f9a03": [
      9,
      5,
      28,
      22,
      26,
      24,
      27
    ],
    "452a2b8f": [
      9,
      5,
      28,
      22,
      26,
      24,
      27
    ],
    "0efbd2ef": [
      9,
      5,
      28,
      22,
      26,
      24,
      27
    ],
    "e0c8224c": [
      9,
      5,
      28,
      22,
      26,
      24,
      27
    ],
    "09274318": [
      9,
      5,
      28,
      22,
      26,
      24,
      27
    ],
    "77f2900c": [
      9,
      5,
      28,
      22,
      26,
      24,
      27
    ],
    "72aff94b": [
      9,
      5,
      28,
      22,
      26,
      24,
      27
    ],
    "818ed8ba": [
      9,
      5,
      28,
      22,
      26,
      24,
      27
    ],
    "5465f5df": [
      9,
      5,
      28,
      22,
      26,
      24,
      27
    ],
    "751c2709": [
      9,
      5,
      28,
      22,
      26,
      24,
      27
    ],
    "ccd3b180": [
      9,
      5,
      28,
      22,
      26,
      24,
      27
    ],
    "245af2bc": [
      9,
      5,
      28,
      22,
      26,
      24,
      27
    ],
    "0fa1d6d6": [
      9,
      5,
      28,
      22,
      26,
      24,
      27
    ],
    "72bd9bc0": [
      9,
      5,
      28,
      22,
      26,
      24,
      27
    ],
    "14e63ba2": [
      10
    ],
    "604953e5": [
      10
    ],
    "a9c23a78": [
      10
    ],
    "6e29aed6": [
      10
    ],
    "44257bb4": [
      10
    ],
    "53ab8bca": [
      10
    ],
    "7066d779": [
      10
    ],
    "70b2f02c": [
      10
    ],
    "285c936e": [
      10
    ],
    "14e36268": [
      10
    ],
    "32f9ea52": [
      10
    ],
    "9fe3e64c": [
      10
    ],
    "44cd5a48": [
      4,
      15,
      23,
      25
    ],
    "041a0278": [
      4,
      15,
      23,
      25
    ],
    "35d82322": [
      4,
      15,
      23,
      25
    ],
    "46ead5d6": [
      4,
      15,
      23,
      25
    ],
    "539b4578": [
      4,
      15,
      23,
      25
    ],
    "514be4c6": [
      4,
      15,
      23,
      25
    ],
    "49bac7d4": [
      4,
      15,
      23,
      25
    ],
    "72d59985": [
      4,
      15,
      23,
      25
    ],
    "4de8b7aa": [
      4,
      15,
      23,
      25
    ],
    "1c30d898": [
      10
    ],
    "55e6f0d7": [
      10
    ],
    "20cc4f19": [
      10
    ],
    "79f3a6e0": [
      10
    ],
    "2ac56c16": [
      10
    ],
    "b6829372": [
      10
    ],
    "639689e9": [
      10
    ],
    "ce20ba2e": [
      10
    ],
    "a259fade": [
      10
    ],
    "2a86f71d": [
      10
    ],
    "2bb5a19d": [
      10
    ],
    "e3e9cd22": [
      10
    ],
    "18193afa": [
      10
    ],
    "dfd28ec6": [
      4,
      15,
      23,
      25
    ],
    "a056a0d8": [
      10
    ],
    "01cd6653": [
      10
    ],
    "8668cb98": [
      10
    ],
    "dd16784e": [
      10
    ],
    "645024ba": [
      10
    ],
    "d86dcb0a": [
      10
    ],
    "f7e34828": [
      10
    ],
    "05f02b80": [
      10
    ],
    "4d7b9442": [
      10
    ],
    "2a094fe0": [
      10
    ],
    "05d026c2": [
      10
    ],
    "a67e6590": [
      10
    ],
    "18008b8f": [
      10
    ],
    "3a9b301b": [
      10
    ],
    "60a2f766": [
      10
    ],
    "6aba0758": [
      10
    ],
    "05c112e9": [
      10
    ],
    "4cad61f2": [
      10
    ],
    "1338c309": [
      10
    ],
    "c33ef840": [
      10
    ],
    "7f91c1ca": [
      10
    ],
    "5ebd1ab5": [
      10
    ],
    "34b20ec6": [
      9,
      5,
      28,
      22,
      26,
      24,
      27
    ],
    "e25a71e6": [
      10
    ],
    "ca0009ae": [
      10
    ],
    "3eec47c7": [
      10
    ],
    "8799efa2": [
      10
    ],
    "59685c9c": [
      10
    ],
    "e85f6078": [
      10
    ],
    "729d8a9e": [
      10
    ],
    "18e91f49": [
      4,
      15,
      23,
      25
    ],
    "712e3f1e": [
      4,
      15,
      23,
      25
    ],
    "a123ad56": [
      4,
      15,
      23,
      25
    ],
    "5e5456f8": [
      4,
      15,
      23,
      25
    ],
    "9964850c": [
      4,
      15,
      23,
      25
    ],
    "f799e402": [
      4,
      15,
      23,
      25
    ],
    "620eac0e": [
      4,
      15,
      23,
      25
    ],
    "6b229adc": [
      4,
      15,
      23,
      25
    ],
    "ab7f4016": [
      10
    ],
    "5196b105": [
      10
    ],
    "3d10c2b8": [
      10
    ],
    "36d8dbda": [
      10
    ],
    "10e24788": [
      10
    ],
    "2a4f6032": [
      10
    ],
    "950f49c4": [
      10
    ],
    "bd407c10": [
      10
    ],
    "ce2545e4": [
      10
    ],
    "17ec2d51": [
      4,
      15,
      23,
      25
    ],
    "132733de": [
      4,
      15,
      23,
      25
    ],
    "717d0b53": [
      4,
      15,
      23,
      25
    ],
    "3add1ee7": [
      4,
      15,
      23,
      25
    ],
    "6a7e83a1": [
      10
    ],
    "ed9ed7d4": [
      10
    ],
    "1393aba2": [
      4,
      15,
      23,
      25
    ],
    "d7113b90": [
      4,
      15,
      23,
      25
    ],
    "1417126d": [
      4,
      15,
      23,
      25
    ],
    "2369c7c6": [
      4,
      15,
      23,
      25
    ],
    "6a894a6f": [
      9,
      5,
      28,
      22,
      26,
      24,
      27
    ],
    "80585fb0": [
      9,
      5,
      28,
      22,
      26,
      24,
      27
    ],
    "0e87c15d": [
      10
    ],
    "71bfcb72": [
      10
    ],
    "7a6f5792": [
      10
    ],
    "10fdbc15": [
      10
    ],
    "7f8c0ff3": [
      10
    ],
    "6e05a3ba": [
      10
    ],
    "25c99555": [
      10
    ],
    "7ba5a7db": [
      10
    ],
    "d07dff04": [
      10
    ],
    "d6ba884c": [
      10
    ],
    "74e3353c": [
      10
    ],
    "d9996992": [
      10
    ],
    "9ce96916": [
      10
    ],
    "3d2e680e": [
      10
    ],
    "8998d260": [
      10
    ],
    "571f7090": [
      10
    ],
    "4da8ba74": [
      10
    ],
    "3b1f9eac": [
      10
    ],
    "541faa93": [
      10
    ],
    "7339267a": [
      10
    ],
    "152d86a8": [
      10
    ],
    "1149aec9": [
      10
    ],
    "4205df2a": [
      10
    ],
    "35b5b872": [
      10
    ],
    "7b5009f4": [
      10
    ],
    "7e99861f": [
      10
    ],
    "4bc340ac": [
      9,
      5,
      28,
      22,
      26,
      24,
      27
    ],
    "78c37750": [
      10
    ],
    "fa2551c6": [
      10
    ],
    "4817614e": [
      10
    ],
    "1fcd1a98": [
      10
    ],
    "a72145a8": [
      10
    ],
    "3362c708": [
      10
    ],
    "2f1ed929": [
      10
    ],
    "69a590c6": [
      10
    ],
    "b37168f4": [
      10
    ],
    "b458a33a": [
      10
    ],
    "4175ba81": [
      10
    ],
    "6c501908": [
      10
    ],
    "7838dd62": [
      9,
      5,
      28,
      22,
      26,
      24,
      27
    ],
    "6b7b2e4a": [
      9,
      5,
      28,
      22,
      26,
      24,
      27
    ],
    "1b239edf": [
      4,
      15,
      23,
      25
    ],
    "30ebb238": [
      9,
      5,
      28,
      22,
      26,
      24,
      27
    ],
    "03041964": [
      9,
      5,
      28,
      22,
      26,
      24,
      27
    ],
    "8431e332": [
      9,
      5,
      28,
      22,
      26,
      24,
      27
    ],
    "ab736872": [
      9,
      5,
      28,
      22,
      26,
      24,
      27
    ],
    "4938b09c": [
      9,
      5,
      28,
      22,
      26,
      24,
      27
    ],
    "4edb7ff0": [
      9,
      5,
      28,
      22,
      26,
      24,
      27
    ],
    "4df0c022": [
      9,
      5,
      28,
      22,
      26,
      24,
      27
    ],
    "38f9511a": [
      9,
      5,
      28,
      22,
      26,
      24,
      27
    ],
    "fbf3b30a": [
      9,
      5,
      28,
      22,
      26,
      24,
      27
    ],
    "1eb48de1": [
      9,
      5,
      28,
      22,
      26,
      24,
      27
    ],
    "9444f04e": [
      9,
      5,
      28,
      22,
      26,
      24,
      27
    ],
    "5f8d5644": [
      9,
      5,
      28,
      22,
      26,
      24,
      27
    ],
    "ad500792": [
      10
    ],
    "7e7b7cc8": [
      10
    ],
    "43d5df88": [
      10
    ],
    "7d1beb49": [
      10
    ],
    "5d7edce8": [
      10
    ],
    "6858bf5f": [
      10
    ],
    "73135af6": [
      10
    ],
    "03c38ebc": [
      10
    ],
    "2fd2b536": [
      10
    ],
    "2924ea81": [
      10
    ],
    "f055c992": [
      10
    ],
    "95cfa1da": [
      10
    ],
    "2ee2c9b5": [
      10
    ],
    "5313d904": [
      10
    ],
    "a5ecd552": [
      10
    ],
    "5935b3d6": [
      4,
      15,
      23,
      25
    ],
    "2d12002e": [
      4,
      15,
      23,
      25
    ],
    "3fec5b78": [
      4,
      15,
      23,
      25
    ],
    "02f9ffd3": [
      4,
      15,
      23,
      25
    ],
    "d3088f4a": [
      4,
      15,
      23,
      25
    ],
    "66da350b": [
      4,
      15,
      23,
      25
    ],
    "202f46f0": [
      4,
      15,
      23,
      25
    ],
    "3186eda5": [
      4,
      15,
      23,
      25
    ],
    "0126b735": [
      4,
      15,
      23,
      25
    ],
    "5415fdaa": [
      4,
      15,
      23,
      25
    ],
    "19dfc9ee": [
      4,
      15,
      23,
      25
    ],
    "503a707e": [
      4,
      15,
      23,
      25
    ],
    "778a704d": [
      4,
      15,
      23,
      25
    ],
    "2eb4461e": [
      4,
      15,
      23,
      25
    ],
    "ff005156": [
      4,
      15,
      23,
      25
    ],
    "190d36e4": [
      4,
      15,
      23,
      25
    ],
    "8d922634": [
      4,
      15,
      23,
      25
    ],
    "e5048a66": [
      4,
      15,
      23,
      25
    ],
    "697b7c9f": [
      4,
      15,
      23,
      25
    ],
    "25bf8712": [
      4,
      15,
      23,
      25
    ],
    "071c58cd": [
      4,
      15,
      23,
      25
    ],
    "64916f72": [
      4,
      15,
      23,
      25
    ],
    "109a71ac": [
      4,
      15,
      23,
      25
    ],
    "78a4c02b": [
      4,
      15,
      23,
      25
    ],
    "0eded5a0": [
      4,
      15,
      23,
      25
    ],
    "dc91e440": [
      10
    ],
    "cddfdc1a": [
      10
    ],
    "1130ebbb": [
      10
    ],
    "c76e27f0": [
      10
    ],
    "5b7a0db6": [
      10
    ],
    "718321ad": [
      10
    ],
    "0195f58a": [
      10
    ],
    "18ee92b4": [
      10
    ],
    "18c4fc2a": [
      4,
      15,
      23,
      25
    ],
    "023008da": [
      10
    ],
    "640cd59a": [
      10
    ],
    "cb7c755e": [
      10
    ],
    "20e725d3": [
      10
    ],
    "1cebfe81": [
      10
    ],
    "2603de34": [
      10
    ],
    "bf6ee5aa": [
      10
    ],
    "428c06ba": [
      10
    ],
    "080bb7fa": [
      10
    ],
    "389969fe": [
      10
    ],
    "23d253cc": [
      4,
      15,
      23,
      25
    ],
    "80b25918": [
      10
    ],
    "4c178b65": [
      10
    ],
    "0c3019e7": [
      10
    ],
    "31bbd87c": [
      10
    ],
    "369c0054": [
      10
    ],
    "3cc99a3a": [
      10
    ],
    "ce2e5d50": [
      10
    ],
    "5d93276e": [
      10
    ],
    "0ca1730a": [
      10
    ],
    "1e44acd7": [
      10
    ],
    "0879de14": [
      4,
      15,
      23,
      25
    ],
    "e999cee6": [
      4,
      15,
      23,
      25
    ],
    "2bb07127": [
      4,
      15,
      23,
      25
    ],
    "eac90df8": [
      4,
      15,
      23,
      25
    ],
    "2e62d29c": [
      4,
      15,
      23,
      25
    ],
    "415127ff": [
      4,
      15,
      23,
      25
    ],
    "9e93b14a": [
      4,
      15,
      23,
      25
    ],
    "03f8766e": [
      4,
      15,
      23,
      25
    ],
    "8245525e": [
      4,
      15,
      23,
      25
    ],
    "3142183c": [
      4,
      15,
      23,
      25
    ],
    "8091dddc": [
      4,
      15,
      23,
      25
    ],
    "54ff0daa": [
      4,
      15,
      23,
      25
    ],
    "3dc410b3": [
      4,
      15,
      23,
      25
    ],
    "1e7c102c": [
      4,
      15,
      23,
      25
    ],
    "1f804846": [
      4,
      15,
      23,
      25
    ],
    "6f1ee6ff": [
      4,
      15,
      23,
      25
    ],
    "ab818c3c": [
      4,
      15,
      23,
      25
    ],
    "cc448c18": [
      4,
      15,
      23,
      25
    ],
    "0c408ff2": [
      4,
      15,
      23,
      25
    ],
    "2d91784b": [
      4,
      15,
      23,
      25
    ],
    "7dcccbb6": [
      4,
      15,
      23,
      25
    ],
    "045b42d8": [
      4,
      15,
      23,
      25
    ],
    "38393f19": [
      4,
      15,
      23,
      25
    ],
    "3b815e2a": [
      4,
      15,
      23,
      25
    ],
    "a92a719c": [
      4,
      15,
      23,
      25
    ],
    "0af03dd8": [
      4,
      15,
      23,
      25
    ],
    "dbaab292": [
      4,
      15,
      23,
      25
    ],
    "2ac636c0": [
      4,
      15,
      23,
      25
    ],
    "6631f790": [
      4,
      15,
      23,
      25
    ],
    "1dcaf826": [
      4,
      15,
      23,
      25
    ],
    "aee614e6": [
      17,
      7
    ],
    "18b3b816": [
      12,
      16
    ],
    "638b279c": [
      18,
      3
    ],
    "11cd9ac6": [
      18,
      3
    ],
    "5bc5792e": [
      11
    ],
    "a350eb36": [
      17,
      7
    ],
    "5b22fb75": [
      6,
      20
    ],
    "7b67c224": [
      12,
      16
    ],
    "1a02250a": [
      18,
      3
    ],
    "261bbaee": [
      18,
      3
    ],
    "e5231c72": [
      18,
      3
    ],
    "5164493c": [
      18,
      3
    ],
    "41b22bfc": [
      18,
      3
    ],
    "4dec2a4a": [
      18,
      3
    ],
    "498a3a9e": [
      18,
      3
    ],
    "5b0ee532": [
      18,
      3
    ],
    "5543fa9c": [
      18,
      3
    ],
    "47f9e62f": [
      18,
      3
    ],
    "1f64924e": [
      18,
      3
    ],
    "715c9713": [
      18,
      3
    ],
    "5b1d9d7a": [
      17,
      7
    ],
    "df872932": [
      17,
      7
    ],
    "77cdd632": [
      17,
      7
    ],
    "3a475fce": [
      17,
      7
    ],
    "6e2a1fcb": [
      17,
      7
    ],
    "9018d0a8": [
      19
    ],
    "040b8239": [
      19
    ],
    "85c36e16": [
      19
    ],
    "f434842a": [
      19
    ],
    "dfb17c4e": [
      19
    ],
    "a5126686": [
      2
    ],
    "636744a8": [
      2
    ],
    "f482fff8": [
      2
    ],
    "0ef44444": [
      2
    ],
    "208f3c30": [
      2
    ],
    "6b57f474": [
      6,
      20
    ],
    "10e187e5": [
      6,
      20
    ],
    "3345323a": [
      6,
      20
    ],
    "23ea56f3": [
      6,
      20
    ],
    "4779137f": [
      6,
      20
    ],
    "33c61554": [
      12,
      16
    ],
    "7131a7f8": [
      12,
      16
    ],
    "ac852cea": [
      12,
      16
    ],
    "7f48d62a": [
      12,
      16
    ],
    "3d39276f": [
      12,
      16
    ],
    "24e21eac": [
      21
    ],
    "894898d2": [
      21
    ],
    "e02b6616": [
      21
    ],
    "6d1a3c6e": [
      21
    ],
    "23660ad9": [
      21
    ],
    "2de1dd94": [
      13
    ],
    "3c6e61f6": [
      13
    ],
    "332b81e6": [
      13
    ],
    "0c024f37": [
      13
    ],
    "506420f1": [
      13
    ],
    "71da6fe0": [
      9,
      5,
      28,
      22,
      26,
      24,
      27
    ],
    "6a1be392": [
      4,
      15,
      23,
      25
    ],
    "5df829e8": [
      9,
      5,
      28,
      22,
      26,
      24,
      27
    ],
    "f1e16fc2": [
      9,
      5,
      28,
      22,
      26,
      24,
      27
    ],
    "715babab": [
      9,
      5,
      28,
      22,
      26,
      24,
      27
    ],
    "677c9ef0": [
      9,
      5,
      28,
      22,
      26,
      24,
      27
    ],
    "8245149c": [
      9,
      5,
      28,
      22,
      26,
      24,
      27
    ],
    "0ac07854": [
      9,
      5,
      28,
      22,
      26,
      24,
      27
    ],
    "2a5abe9a": [
      17,
      7
    ],
    "247b91a0": [
      6,
      20
    ],
    "c391563a": [
      12,
      16
    ],
    "17fcf619": [
      18,
      3
    ],
    "9ff5c15c": [
      9,
      5,
      28,
      22,
      26,
      24,
      27
    ],
    "9ed4a1b6": [
      9,
      5,
      28,
      22,
      26,
      24,
      27
    ],
    "8de1e244": [
      9,
      5,
      28,
      22,
      26,
      24,
      27
    ],
    "240e2cbf": [
      18,
      3
    ],
    "1fcbcad2": [
      9,
      5,
      28,
      22,
      26,
      24,
      27
    ],
    "750ffcdc": [
      9,
      5,
      28,
      22,
      26,
      24,
      27
    ],
    "3520a132": [
      9,
      5,
      28,
      22,
      26,
      24,
      27
    ]
  },
  "assetsMapping": {
    "173c8518f9810d63acf7.js": "3d94028a",
    "1b877d8caa268cf1e76c.js": "bead0c72",
    "246b415b69c4f9dcfda1.js": "1a3ae26b",
    "460721a3edf09a936742.js": "585221f2",
    "4e00b2bf83a22b3439a8.js": "6fca0322",
    "854140c5106254de9cbd.js": "0859c165",
    "892785931ff60af9a7c5.js": "bba68bf6",
    "9863655425b21475c934.js": "3cdf16e1",
    "b6a66e511381062c8f05.js": "7ea1d828",
    "c878daac161a8e7b12ea.js": "661010b4",
    "f150bdb1bf9ca2193980.js": "8274908e",
    "f36a208bc59d00589b6f.js": "4ce77d46",
    "fc2e6f15a5142ddc50bf.js": "33798808"
  }
}